{
    "/func0#0": {
        "dim": 2,
        "trainingsize": 30,
        "m": 2,
        "pcoeff": [
            0.042364004496069904,
            -0.003247970561100789,
            -0.02029783065814713,
            -0.003906624158221856,
            -0.00046956530642673806,
            -0.0003905555400925684
        ],
        "scaler": {
            "a": [
                -1.0,
                -1.0
            ],
            "b": [
                1.0,
                1.0
            ],
            "Xmin": [
                1.0068764806376422,
                -1.1834862458328574
            ],
            "Xmax": [
                1.9587767435001249,
                -0.8066343532552543
            ],
            "scaleTerm": [
                2.101060455625625,
                5.307124733593186
            ],
            "pnames": [
                "a",
                "b"
            ]
        },
        "vmin": 0.019467358435197226,
        "vmax": 0.06614003662264215,
        "xmin": 0.0,
        "xmax": 0.15
    },
    "/func0#1": {
        "dim": 2,
        "trainingsize": 30,
        "m": 2,
        "pcoeff": [
            0.0425408341948787,
            0.001893471601344946,
            -0.022178578700159518,
            0.0012177669103856767,
            -0.004163615124376458,
            0.0002766327684569597
        ],
        "scaler": {
            "a": [
                -1.0,
                -1.0
            ],
            "b": [
                1.0,
                1.0
            ],
            "Xmin": [
                1.0068764806376422,
                -1.1834862458328574
            ],
            "Xmax": [
                1.9587767435001249,
                -0.8066343532552543
            ],
            "scaleTerm": [
                2.101060455625625,
                5.307124733593186
            ],
            "pnames": [
                "a",
                "b"
            ]
        },
        "vmin": 0.020083298755156954,
        "vmax": 0.0782451986457387,
        "xmin": 0.15,
        "xmax": 0.3
    },
    "/func0#2": {
        "dim": 2,
        "trainingsize": 30,
        "m": 2,
        "pcoeff": [
            0.04117351659903045,
            0.004820037281143182,
            -0.023584231767286936,
            0.008793069830122974,
            0.0026012413005780423,
            0.006084315068139846
        ],
        "scaler": {
            "a": [
                -1.0,
                -1.0
            ],
            "b": [
                1.0,
                1.0
            ],
            "Xmin": [
                1.0068764806376422,
                -1.1834862458328574
            ],
            "Xmax": [
                1.9587767435001249,
                -0.8066343532552543
            ],
            "scaleTerm": [
                2.101060455625625,
                5.307124733593186
            ],
            "pnames": [
                "a",
                "b"
            ]
        },
        "vmin": 0.02140327077808436,
        "vmax": 0.07550090507183783,
        "xmin": 0.3,
        "xmax": 0.45
    },
    "/func0#3": {
        "dim": 2,
        "trainingsize": 30,
        "m": 2,
        "pcoeff": [
            0.05414705378615489,
            0.0012370509012390443,
            -0.019593450261352705,
            -0.006777450524665661,
            0.0008689154330570998,
            -0.00354284029654312
        ],
        "scaler": {
            "a": [
                -1.0,
                -1.0
            ],
            "b": [
                1.0,
                1.0
            ],
            "Xmin": [
                1.0068764806376422,
                -1.1834862458328574
            ],
            "Xmax": [
                1.9587767435001249,
                -0.8066343532552543
            ],
            "scaleTerm": [
                2.101060455625625,
                5.307124733593186
            ],
            "pnames": [
                "a",
                "b"
            ]
        },
        "vmin": 0.02129222080166056,
        "vmax": 0.07547779658798857,
        "xmin": 0.45,
        "xmax": 0.6
    },
    "/func0#4": {
        "dim": 2,
        "trainingsize": 30,
        "m": 2,
        "pcoeff": [
            0.04980912107636556,
            0.0011353348867668873,
            -0.018617458286564217,
            2.3334787915161247e-05,
            0.0043953155790256385,
            0.002537739177226752
        ],
        "scaler": {
            "a": [
                -1.0,
                -1.0
            ],
            "b": [
                1.0,
                1.0
            ],
            "Xmin": [
                1.0068764806376422,
                -1.1834862458328574
            ],
            "Xmax": [
                1.9587767435001249,
                -0.8066343532552543
            ],
            "scaleTerm": [
                2.101060455625625,
                5.307124733593186
            ],
            "pnames": [
                "a",
                "b"
            ]
        },
        "vmin": 0.030315181381977942,
        "vmax": 0.07182642658211219,
        "xmin": 0.6,
        "xmax": 0.75
    },
    "/func0#5": {
        "dim": 2,
        "trainingsize": 30,
        "m": 2,
        "pcoeff": [
            0.04841634547359608,
            0.003905686873768753,
            -0.01759727972380127,
            -0.0005471714988402869,
            -0.004981741990320149,
            0.0032594031237016124
        ],
        "scaler": {
            "a": [
                -1.0,
                -1.0
            ],
            "b": [
                1.0,
                1.0
            ],
            "Xmin": [
                1.0068764806376422,
                -1.1834862458328574
            ],
            "Xmax": [
                1.9587767435001249,
                -0.8066343532552543
            ],
            "scaleTerm": [
                2.101060455625625,
                5.307124733593186
            ],
            "pnames": [
                "a",
                "b"
            ]
        },
        "vmin": 0.028539306228428186,
        "vmax": 0.0719862332517668,
        "xmin": 0.75,
        "xmax": 0.9
    },
    "/func0#6": {
        "dim": 2,
        "trainingsize": 30,
        "m": 2,
        "pcoeff": [
            0.05049632182820461,
            0.001501594360732749,
            -0.01622907101233032,
            0.0016065676504466427,
            -9.149734840518898e-05,
            -0.003345341628859083
        ],
        "scaler": {
            "a": [
                -1.0,
                -1.0
            ],
            "b": [
                1.0,
                1.0
            ],
            "Xmin": [
                1.0068764806376422,
                -1.1834862458328574
            ],
            "Xmax": [
                1.9587767435001249,
                -0.8066343532552543
            ],
            "scaleTerm": [
                2.101060455625625,
                5.307124733593186
            ],
            "pnames": [
                "a",
                "b"
            ]
        },
        "vmin": 0.02882119590394079,
        "vmax": 0.07160431396066703,
        "xmin": 0.9,
        "xmax": 1.05
    },
    "/func0#7": {
        "dim": 2,
        "trainingsize": 30,
        "m": 2,
        "pcoeff": [
            0.04631737521150893,
            0.008134249722823606,
            -0.01575136038841696,
            0.0017405079013785634,
            0.0005393555981018051,
            0.0022215410101838243
        ],
        "scaler": {
            "a": [
                -1.0,
                -1.0
            ],
            "b": [
                1.0,
                1.0
            ],
            "Xmin": [
                1.0068764806376422,
                -1.1834862458328574
            ],
            "Xmax": [
                1.9587767435001249,
                -0.8066343532552543
            ],
            "scaleTerm": [
                2.101060455625625,
                5.307124733593186
            ],
            "pnames": [
                "a",
                "b"
            ]
        },
        "vmin": 0.025282193997620817,
        "vmax": 0.07021997183454612,
        "xmin": 1.05,
        "xmax": 1.2
    },
    "/func0#8": {
        "dim": 2,
        "trainingsize": 30,
        "m": 2,
        "pcoeff": [
            0.04191509614992783,
            0.010714508916624281,
            -0.01134221025843717,
            0.004153538123369684,
            -0.00505476750282703,
            -0.003940677748889449
        ],
        "scaler": {
            "a": [
                -1.0,
                -1.0
            ],
            "b": [
                1.0,
                1.0
            ],
            "Xmin": [
                1.0068764806376422,
                -1.1834862458328574
            ],
            "Xmax": [
                1.9587767435001249,
                -0.8066343532552543
            ],
            "scaleTerm": [
                2.101060455625625,
                5.307124733593186
            ],
            "pnames": [
                "a",
                "b"
            ]
        },
        "vmin": 0.027610247694973267,
        "vmax": 0.05863097399081057,
        "xmin": 1.2,
        "xmax": 1.35
    },
    "/func0#9": {
        "dim": 2,
        "trainingsize": 30,
        "m": 2,
        "pcoeff": [
            0.03823796643591068,
            0.008761897997524793,
            -0.011008496452118191,
            0.004607607005228085,
            0.003261369597277761,
            0.001430470417465805
        ],
        "scaler": {
            "a": [
                -1.0,
                -1.0
            ],
            "b": [
                1.0,
                1.0
            ],
            "Xmin": [
                1.0068764806376422,
                -1.1834862458328574
            ],
            "Xmax": [
                1.9587767435001249,
                -0.8066343532552543
            ],
            "scaleTerm": [
                2.101060455625625,
                5.307124733593186
            ],
            "pnames": [
                "a",
                "b"
            ]
        },
        "vmin": 0.020494688742858893,
        "vmax": 0.05526369513523325,
        "xmin": 1.35,
        "xmax": 1.5
    },
    "/func0#10": {
        "dim": 2,
        "trainingsize": 30,
        "m": 2,
        "pcoeff": [
            0.036511621993155885,
            0.008707182462419367,
            -0.004665275409917259,
            -0.0005450200236119364,
            -0.0009089021526351306,
            -0.0007272831265880504
        ],
        "scaler": {
            "a": [
                -1.0,
                -1.0
            ],
            "b": [
                1.0,
                1.0
            ],
            "Xmin": [
                1.0068764806376422,
                -1.1834862458328574
            ],
            "Xmax": [
                1.9587767435001249,
                -0.8066343532552543
            ],
            "scaleTerm": [
                2.101060455625625,
                5.307124733593186
            ],
            "pnames": [
                "a",
                "b"
            ]
        },
        "vmin": 0.020211006902180813,
        "vmax": 0.04918460915548461,
        "xmin": 1.5,
        "xmax": 1.65
    },
    "/func0#11": {
        "dim": 2,
        "trainingsize": 30,
        "m": 2,
        "pcoeff": [
            0.029558094066556996,
            0.010242808015132103,
            -0.004933705495720712,
            0.005814913840473563,
            -0.0006606358072106192,
            -0.0011616311799089556
        ],
        "scaler": {
            "a": [
                -1.0,
                -1.0
            ],
            "b": [
                1.0,
                1.0
            ],
            "Xmin": [
                1.0068764806376422,
                -1.1834862458328574
            ],
            "Xmax": [
                1.9587767435001249,
                -0.8066343532552543
            ],
            "scaleTerm": [
                2.101060455625625,
                5.307124733593186
            ],
            "pnames": [
                "a",
                "b"
            ]
        },
        "vmin": 0.015506263967256,
        "vmax": 0.0466725234420043,
        "xmin": 1.65,
        "xmax": 1.8
    },
    "/func0#12": {
        "dim": 2,
        "trainingsize": 30,
        "m": 2,
        "pcoeff": [
            0.027610855152665655,
            0.011580941754488965,
            -0.005109947653741147,
            0.0033101681431199816,
            -0.007654634976962124,
            -0.006344566444143195
        ],
        "scaler": {
            "a": [
                -1.0,
                -1.0
            ],
            "b": [
                1.0,
                1.0
            ],
            "Xmin": [
                1.0068764806376422,
                -1.1834862458328574
            ],
            "Xmax": [
                1.9587767435001249,
                -0.8066343532552543
            ],
            "scaleTerm": [
                2.101060455625625,
                5.307124733593186
            ],
            "pnames": [
                "a",
                "b"
            ]
        },
        "vmin": 0.01528915229101267,
        "vmax": 0.044904080487684496,
        "xmin": 1.8,
        "xmax": 1.95
    },
    "/func0#13": {
        "dim": 2,
        "trainingsize": 30,
        "m": 2,
        "pcoeff": [
            0.022184322752048125,
            0.008136169872250808,
            -0.0013279802054416616,
            0.00036231283188027565,
            0.0023049377984231544,
            -0.0008120811062629386
        ],
        "scaler": {
            "a": [
                -1.0,
                -1.0
            ],
            "b": [
                1.0,
                1.0
            ],
            "Xmin": [
                1.0068764806376422,
                -1.1834862458328574
            ],
            "Xmax": [
                1.9587767435001249,
                -0.8066343532552543
            ],
            "scaleTerm": [
                2.101060455625625,
                5.307124733593186
            ],
            "pnames": [
                "a",
                "b"
            ]
        },
        "vmin": 0.012510614160250743,
        "vmax": 0.036165238067022897,
        "xmin": 1.95,
        "xmax": 2.1
    },
    "/func0#14": {
        "dim": 2,
        "trainingsize": 30,
        "m": 2,
        "pcoeff": [
            0.017830482175130457,
            0.00802917196501139,
            -0.00043627268491131356,
            -5.384588337634805e-05,
            0.0005792300827458331,
            0.0008765329925175085
        ],
        "scaler": {
            "a": [
                -1.0,
                -1.0
            ],
            "b": [
                1.0,
                1.0
            ],
            "Xmin": [
                1.0068764806376422,
                -1.1834862458328574
            ],
            "Xmax": [
                1.9587767435001249,
                -0.8066343532552543
            ],
            "scaleTerm": [
                2.101060455625625,
                5.307124733593186
            ],
            "pnames": [
                "a",
                "b"
            ]
        },
        "vmin": 0.009020778483282057,
        "vmax": 0.02788534461763823,
        "xmin": 2.1,
        "xmax": 2.25
    },
    "/func0#15": {
        "dim": 2,
        "trainingsize": 30,
        "m": 2,
        "pcoeff": [
            0.014615618061898629,
            0.007707941043670548,
            0.00027029262372475055,
            0.0018935197558694198,
            0.002160171218677218,
            -0.0008922447002144992
        ],
        "scaler": {
            "a": [
                -1.0,
                -1.0
            ],
            "b": [
                1.0,
                1.0
            ],
            "Xmin": [
                1.0068764806376422,
                -1.1834862458328574
            ],
            "Xmax": [
                1.9587767435001249,
                -0.8066343532552543
            ],
            "scaleTerm": [
                2.101060455625625,
                5.307124733593186
            ],
            "pnames": [
                "a",
                "b"
            ]
        },
        "vmin": 0.007521551258439538,
        "vmax": 0.02626033764697884,
        "xmin": 2.25,
        "xmax": 2.4
    },
    "/func0#16": {
        "dim": 2,
        "trainingsize": 30,
        "m": 2,
        "pcoeff": [
            0.011313853861790974,
            0.0071067816154031386,
            0.0011032969273839504,
            0.00163637141468334,
            -0.0002990296048136357,
            0.00029713606567464577
        ],
        "scaler": {
            "a": [
                -1.0,
                -1.0
            ],
            "b": [
                1.0,
                1.0
            ],
            "Xmin": [
                1.0068764806376422,
                -1.1834862458328574
            ],
            "Xmax": [
                1.9587767435001249,
                -0.8066343532552543
            ],
            "scaleTerm": [
                2.101060455625625,
                5.307124733593186
            ],
            "pnames": [
                "a",
                "b"
            ]
        },
        "vmin": 0.005285188948582847,
        "vmax": 0.021344986400661983,
        "xmin": 2.4,
        "xmax": 2.55
    },
    "/func0#17": {
        "dim": 2,
        "trainingsize": 30,
        "m": 2,
        "pcoeff": [
            0.009142309913136347,
            0.005453941343491496,
            0.0002486057014227359,
            0.0010540634052854147,
            0.00012026601098836539,
            -0.0011335590124794304
        ],
        "scaler": {
            "a": [
                -1.0,
                -1.0
            ],
            "b": [
                1.0,
                1.0
            ],
            "Xmin": [
                1.0068764806376422,
                -1.1834862458328574
            ],
            "Xmax": [
                1.9587767435001249,
                -0.8066343532552543
            ],
            "scaleTerm": [
                2.101060455625625,
                5.307124733593186
            ],
            "pnames": [
                "a",
                "b"
            ]
        },
        "vmin": 0.0037621105187853657,
        "vmax": 0.016924777366006546,
        "xmin": 2.55,
        "xmax": 2.7
    },
    "/func0#18": {
        "dim": 2,
        "trainingsize": 30,
        "m": 2,
        "pcoeff": [
            0.006983096474833507,
            0.004788619867985319,
            0.001357436341291191,
            0.0005055055140469685,
            0.0021102315067746593,
            0.00027096429667144506
        ],
        "scaler": {
            "a": [
                -1.0,
                -1.0
            ],
            "b": [
                1.0,
                1.0
            ],
            "Xmin": [
                1.0068764806376422,
                -1.1834862458328574
            ],
            "Xmax": [
                1.9587767435001249,
                -0.8066343532552543
            ],
            "scaleTerm": [
                2.101060455625625,
                5.307124733593186
            ],
            "pnames": [
                "a",
                "b"
            ]
        },
        "vmin": 0.002959919668579614,
        "vmax": 0.015536403130139952,
        "xmin": 2.7,
        "xmax": 2.85
    },
    "/func0#19": {
        "dim": 2,
        "trainingsize": 30,
        "m": 2,
        "pcoeff": [
            0.00436560993608249,
            0.004211250543422911,
            0.00072171413119824,
            0.002016023775702097,
            0.0005037966469646804,
            3.286395207614638e-05
        ],
        "scaler": {
            "a": [
                -1.0,
                -1.0
            ],
            "b": [
                1.0,
                1.0
            ],
            "Xmin": [
                1.0068764806376422,
                -1.1834862458328574
            ],
            "Xmax": [
                1.9587767435001249,
                -0.8066343532552543
            ],
            "scaleTerm": [
                2.101060455625625,
                5.307124733593186
            ],
            "pnames": [
                "a",
                "b"
            ]
        },
        "vmin": 0.0017831113880580275,
        "vmax": 0.011491496372922416,
        "xmin": 2.85,
        "xmax": 3.0
    },
    "/func1#0": {
        "dim": 2,
        "trainingsize": 30,
        "m": 2,
        "pcoeff": [
            0.044083797111135976,
            0.0037710728790960827,
            -0.018245309458798736,
            -0.003168197307027547,
            0.0030088879956611013,
            0.003940559446611284
        ],
        "scaler": {
            "a": [
                -1.0,
                -1.0
            ],
            "b": [
                1.0,
                1.0
            ],
            "Xmin": [
                1.0068764806376422,
                -1.1834862458328574
            ],
            "Xmax": [
                1.9587767435001249,
                -0.8066343532552543
            ],
            "scaleTerm": [
                2.101060455625625,
                5.307124733593186
            ],
            "pnames": [
                "a",
                "b"
            ]
        },
        "vmin": 0.024094388466104625,
        "vmax": 0.07022699702472768,
        "xmin": 0.0,
        "xmax": 0.15
    },
    "/func1#1": {
        "dim": 2,
        "trainingsize": 30,
        "m": 2,
        "pcoeff": [
            0.04766988345981132,
            0.005548127475763705,
            -0.019986306352975554,
            -0.000836507496373796,
            0.0019067924813918429,
            0.006950381500528579
        ],
        "scaler": {
            "a": [
                -1.0,
                -1.0
            ],
            "b": [
                1.0,
                1.0
            ],
            "Xmin": [
                1.0068764806376422,
                -1.1834862458328574
            ],
            "Xmax": [
                1.9587767435001249,
                -0.8066343532552543
            ],
            "scaleTerm": [
                2.101060455625625,
                5.307124733593186
            ],
            "pnames": [
                "a",
                "b"
            ]
        },
        "vmin": 0.02538450971228976,
        "vmax": 0.07822554285881024,
        "xmin": 0.15,
        "xmax": 0.3
    },
    "/func1#2": {
        "dim": 2,
        "trainingsize": 30,
        "m": 2,
        "pcoeff": [
            0.049240311123641724,
            0.003036749848916054,
            -0.021550342118840146,
            -0.0014928066040776366,
            0.001952007535701894,
            0.010521202882352424
        ],
        "scaler": {
            "a": [
                -1.0,
                -1.0
            ],
            "b": [
                1.0,
                1.0
            ],
            "Xmin": [
                1.0068764806376422,
                -1.1834862458328574
            ],
            "Xmax": [
                1.9587767435001249,
                -0.8066343532552543
            ],
            "scaleTerm": [
                2.101060455625625,
                5.307124733593186
            ],
            "pnames": [
                "a",
                "b"
            ]
        },
        "vmin": 0.027991252601879433,
        "vmax": 0.09283059840375905,
        "xmin": 0.3,
        "xmax": 0.45
    },
    "/func1#3": {
        "dim": 2,
        "trainingsize": 30,
        "m": 2,
        "pcoeff": [
            0.059762689576403696,
            0.005039350427227371,
            -0.020294600605219783,
            -0.006791632305996252,
            0.0012347066168219947,
            -0.0015224260588848895
        ],
        "scaler": {
            "a": [
                -1.0,
                -1.0
            ],
            "b": [
                1.0,
                1.0
            ],
            "Xmin": [
                1.0068764806376422,
                -1.1834862458328574
            ],
            "Xmax": [
                1.9587767435001249,
                -0.8066343532552543
            ],
            "scaleTerm": [
                2.101060455625625,
                5.307124733593186
            ],
            "pnames": [
                "a",
                "b"
            ]
        },
        "vmin": 0.02616713800000129,
        "vmax": 0.08392764079186839,
        "xmin": 0.45,
        "xmax": 0.6
    },
    "/func1#4": {
        "dim": 2,
        "trainingsize": 30,
        "m": 2,
        "pcoeff": [
            0.06624112372619415,
            0.0037254425094632084,
            -0.01672125600083201,
            -0.010069027348612852,
            -0.0032712025442656004,
            -0.009774416090274832
        ],
        "scaler": {
            "a": [
                -1.0,
                -1.0
            ],
            "b": [
                1.0,
                1.0
            ],
            "Xmin": [
                1.0068764806376422,
                -1.1834862458328574
            ],
            "Xmax": [
                1.9587767435001249,
                -0.8066343532552543
            ],
            "scaleTerm": [
                2.101060455625625,
                5.307124733593186
            ],
            "pnames": [
                "a",
                "b"
            ]
        },
        "vmin": 0.030755985867253,
        "vmax": 0.08873415977576567,
        "xmin": 0.6,
        "xmax": 0.75
    },
    "/func1#5": {
        "dim": 2,
        "trainingsize": 30,
        "m": 2,
        "pcoeff": [
            0.058151724436479195,
            0.007402692380737311,
            -0.014293477285311764,
            0.0010475749010311905,
            -0.0005738447168845372,
            -0.00017508877803260915
        ],
        "scaler": {
            "a": [
                -1.0,
                -1.0
            ],
            "b": [
                1.0,
                1.0
            ],
            "Xmin": [
                1.0068764806376422,
                -1.1834862458328574
            ],
            "Xmax": [
                1.9587767435001249,
                -0.8066343532552543
            ],
            "scaleTerm": [
                2.101060455625625,
                5.307124733593186
            ],
            "pnames": [
                "a",
                "b"
            ]
        },
        "vmin": 0.0359085071938237,
        "vmax": 0.0809680321004668,
        "xmin": 0.75,
        "xmax": 0.9
    },
    "/func1#6": {
        "dim": 2,
        "trainingsize": 30,
        "m": 2,
        "pcoeff": [
            0.056619103423439406,
            0.00884922082346536,
            -0.01027204228254498,
            -0.0023334964954028065,
            -0.003823899414112757,
            0.003024843268495965
        ],
        "scaler": {
            "a": [
                -1.0,
                -1.0
            ],
            "b": [
                1.0,
                1.0
            ],
            "Xmin": [
                1.0068764806376422,
                -1.1834862458328574
            ],
            "Xmax": [
                1.9587767435001249,
                -0.8066343532552543
            ],
            "scaleTerm": [
                2.101060455625625,
                5.307124733593186
            ],
            "pnames": [
                "a",
                "b"
            ]
        },
        "vmin": 0.038434018496350045,
        "vmax": 0.08346166119176449,
        "xmin": 0.9,
        "xmax": 1.05
    },
    "/func1#7": {
        "dim": 2,
        "trainingsize": 30,
        "m": 2,
        "pcoeff": [
            0.0470255214947482,
            0.00830801825717357,
            -0.011616053519057897,
            0.0030932330727983853,
            0.0007348374048432132,
            -0.003938449156689755
        ],
        "scaler": {
            "a": [
                -1.0,
                -1.0
            ],
            "b": [
                1.0,
                1.0
            ],
            "Xmin": [
                1.0068764806376422,
                -1.1834862458328574
            ],
            "Xmax": [
                1.9587767435001249,
                -0.8066343532552543
            ],
            "scaleTerm": [
                2.101060455625625,
                5.307124733593186
            ],
            "pnames": [
                "a",
                "b"
            ]
        },
        "vmin": 0.023961135198483408,
        "vmax": 0.06392893624086743,
        "xmin": 1.05,
        "xmax": 1.2
    },
    "/func1#8": {
        "dim": 2,
        "trainingsize": 30,
        "m": 2,
        "pcoeff": [
            0.03882715476352677,
            0.009116854682568228,
            -0.006958827412142781,
            -0.0015162761425765517,
            -0.0010044153421990504,
            -0.000916057383567777
        ],
        "scaler": {
            "a": [
                -1.0,
                -1.0
            ],
            "b": [
                1.0,
                1.0
            ],
            "Xmin": [
                1.0068764806376422,
                -1.1834862458328574
            ],
            "Xmax": [
                1.9587767435001249,
                -0.8066343532552543
            ],
            "scaleTerm": [
                2.101060455625625,
                5.307124733593186
            ],
            "pnames": [
                "a",
                "b"
            ]
        },
        "vmin": 0.022901276044020855,
        "vmax": 0.05208169224081206,
        "xmin": 1.2,
        "xmax": 1.35
    },
    "/func1#9": {
        "dim": 2,
        "trainingsize": 30,
        "m": 2,
        "pcoeff": [
            0.026940203398731523,
            0.009096020649211799,
            -0.005039270464779271,
            0.001744869137290577,
            0.005238823003649529,
            0.0024487178867728054
        ],
        "scaler": {
            "a": [
                -1.0,
                -1.0
            ],
            "b": [
                1.0,
                1.0
            ],
            "Xmin": [
                1.0068764806376422,
                -1.1834862458328574
            ],
            "Xmax": [
                1.9587767435001249,
                -0.8066343532552543
            ],
            "scaleTerm": [
                2.101060455625625,
                5.307124733593186
            ],
            "pnames": [
                "a",
                "b"
            ]
        },
        "vmin": 0.014487902999859349,
        "vmax": 0.0467056408679818,
        "xmin": 1.35,
        "xmax": 1.5
    },
    "/func1#10": {
        "dim": 2,
        "trainingsize": 30,
        "m": 2,
        "pcoeff": [
            0.020458667200146493,
            0.00850726132170277,
            -0.002833452392246517,
            0.00263625891336373,
            -0.004062761217717734,
            -0.00394444435983193
        ],
        "scaler": {
            "a": [
                -1.0,
                -1.0
            ],
            "b": [
                1.0,
                1.0
            ],
            "Xmin": [
                1.0068764806376422,
                -1.1834862458328574
            ],
            "Xmax": [
                1.9587767435001249,
                -0.8066343532552543
            ],
            "scaleTerm": [
                2.101060455625625,
                5.307124733593186
            ],
            "pnames": [
                "a",
                "b"
            ]
        },
        "vmin": 0.01061113461312116,
        "vmax": 0.03290837785934358,
        "xmin": 1.5,
        "xmax": 1.65
    },
    "/func1#11": {
        "dim": 2,
        "trainingsize": 30,
        "m": 2,
        "pcoeff": [
            0.01224525488154134,
            0.0066254569012619766,
            -0.0006433614377125165,
            0.0014421988479187704,
            0.0003509960862660835,
            -0.0006930355304749338
        ],
        "scaler": {
            "a": [
                -1.0,
                -1.0
            ],
            "b": [
                1.0,
                1.0
            ],
            "Xmin": [
                1.0068764806376422,
                -1.1834862458328574
            ],
            "Xmax": [
                1.9587767435001249,
                -0.8066343532552543
            ],
            "scaleTerm": [
                2.101060455625625,
                5.307124733593186
            ],
            "pnames": [
                "a",
                "b"
            ]
        },
        "vmin": 0.0056511528813941,
        "vmax": 0.024512101319778976,
        "xmin": 1.65,
        "xmax": 1.8
    },
    "/func1#12": {
        "dim": 2,
        "trainingsize": 30,
        "m": 2,
        "pcoeff": [
            0.006106653707885757,
            0.004856331146311883,
            -0.00023597051295111985,
            0.0026042641160240816,
            0.0001901615425121789,
            0.0002441131055109019
        ],
        "scaler": {
            "a": [
                -1.0,
                -1.0
            ],
            "b": [
                1.0,
                1.0
            ],
            "Xmin": [
                1.0068764806376422,
                -1.1834862458328574
            ],
            "Xmax": [
                1.9587767435001249,
                -0.8066343532552543
            ],
            "scaleTerm": [
                2.101060455625625,
                5.307124733593186
            ],
            "pnames": [
                "a",
                "b"
            ]
        },
        "vmin": 0.0033896423934621145,
        "vmax": 0.014732396651974565,
        "xmin": 1.8,
        "xmax": 1.95
    },
    "/func1#13": {
        "dim": 2,
        "trainingsize": 30,
        "m": 2,
        "pcoeff": [
            0.003275199161437765,
            0.003108648013832688,
            -3.3595735565987385e-05,
            0.0012606174613474283,
            -7.123827589170052e-05,
            -0.0002841159996551676
        ],
        "scaler": {
            "a": [
                -1.0,
                -1.0
            ],
            "b": [
                1.0,
                1.0
            ],
            "Xmin": [
                1.0068764806376422,
                -1.1834862458328574
            ],
            "Xmax": [
                1.9587767435001249,
                -0.8066343532552543
            ],
            "scaleTerm": [
                2.101060455625625,
                5.307124733593186
            ],
            "pnames": [
                "a",
                "b"
            ]
        },
        "vmin": 0.0009947826116516326,
        "vmax": 0.007340684194572353,
        "xmin": 1.95,
        "xmax": 2.1
    },
    "/func1#14": {
        "dim": 2,
        "trainingsize": 30,
        "m": 2,
        "pcoeff": [
            0.0012523540721926043,
            0.0016106919653832877,
            -0.0001388815359870252,
            0.0007930589725868527,
            -0.00010344196430640316,
            0.00030385296741087164
        ],
        "scaler": {
            "a": [
                -1.0,
                -1.0
            ],
            "b": [
                1.0,
                1.0
            ],
            "Xmin": [
                1.0068764806376422,
                -1.1834862458328574
            ],
            "Xmax": [
                1.9587767435001249,
                -0.8066343532552543
            ],
            "scaleTerm": [
                2.101060455625625,
                5.307124733593186
            ],
            "pnames": [
                "a",
                "b"
            ]
        },
        "vmin": 0.0,
        "vmax": 0.004012347054890554,
        "xmin": 2.1,
        "xmax": 2.25
    },
    "/func1#15": {
        "dim": 2,
        "trainingsize": 30,
        "m": 2,
        "pcoeff": [
            0.0003973198113227092,
            0.0006795509987560157,
            0.000252106758580396,
            0.000342142492759032,
            0.0002470524981345783,
            -0.00015721763142166807
        ],
        "scaler": {
            "a": [
                -1.0,
                -1.0
            ],
            "b": [
                1.0,
                1.0
            ],
            "Xmin": [
                1.0068764806376422,
                -1.1834862458328574
            ],
            "Xmax": [
                1.9587767435001249,
                -0.8066343532552543
            ],
            "scaleTerm": [
                2.101060455625625,
                5.307124733593186
            ],
            "pnames": [
                "a",
                "b"
            ]
        },
        "vmin": 0.0,
        "vmax": 0.0018489368717064304,
        "xmin": 2.25,
        "xmax": 2.4
    },
    "/func1#16": {
        "dim": 2,
        "trainingsize": 30,
        "m": 2,
        "pcoeff": [
            1.675715477411724e-05,
            0.0003094021913082885,
            9.506149136629814e-05,
            0.0003492797026840327,
            0.00014661142603028619,
            3.789649966765503e-05
        ],
        "scaler": {
            "a": [
                -1.0,
                -1.0
            ],
            "b": [
                1.0,
                1.0
            ],
            "Xmin": [
                1.0068764806376422,
                -1.1834862458328574
            ],
            "Xmax": [
                1.9587767435001249,
                -0.8066343532552543
            ],
            "scaleTerm": [
                2.101060455625625,
                5.307124733593186
            ],
            "pnames": [
                "a",
                "b"
            ]
        },
        "vmin": 0.0,
        "vmax": 0.0008414997194163398,
        "xmin": 2.4,
        "xmax": 2.55
    },
    "/func1#17": {
        "dim": 2,
        "trainingsize": 30,
        "m": 2,
        "pcoeff": [
            2.729646864507047e-05,
            0.0001404571559585256,
            -6.575920277681868e-05,
            0.00019127593259146851,
            -0.0002242682679576727,
            -0.00013602867864127648
        ],
        "scaler": {
            "a": [
                -1.0,
                -1.0
            ],
            "b": [
                1.0,
                1.0
            ],
            "Xmin": [
                1.0068764806376422,
                -1.1834862458328574
            ],
            "Xmax": [
                1.9587767435001249,
                -0.8066343532552543
            ],
            "scaleTerm": [
                2.101060455625625,
                5.307124733593186
            ],
            "pnames": [
                "a",
                "b"
            ]
        },
        "vmin": 0.0,
        "vmax": 0.0006892230730644775,
        "xmin": 2.55,
        "xmax": 2.7
    },
    "/func1#18": {
        "dim": 2,
        "trainingsize": 30,
        "m": 2,
        "pcoeff": [
            0.0,
            0.0,
            0.0,
            0.0,
            0.0,
            0.0
        ],
        "scaler": {
            "a": [
                -1.0,
                -1.0
            ],
            "b": [
                1.0,
                1.0
            ],
            "Xmin": [
                1.0068764806376422,
                -1.1834862458328574
            ],
            "Xmax": [
                1.9587767435001249,
                -0.8066343532552543
            ],
            "scaleTerm": [
                2.101060455625625,
                5.307124733593186
            ],
            "pnames": [
                "a",
                "b"
            ]
        },
        "vmin": 0.0,
        "vmax": 0.0,
        "xmin": 2.7,
        "xmax": 2.85
    },
    "/func1#19": {
        "dim": 2,
        "trainingsize": 30,
        "m": 2,
        "pcoeff": [
            0.0,
            0.0,
            0.0,
            0.0,
            0.0,
            0.0
        ],
        "scaler": {
            "a": [
                -1.0,
                -1.0
            ],
            "b": [
                1.0,
                1.0
            ],
            "Xmin": [
                1.0068764806376422,
                -1.1834862458328574
            ],
            "Xmax": [
                1.9587767435001249,
                -0.8066343532552543
            ],
            "scaleTerm": [
                2.101060455625625,
                5.307124733593186
            ],
            "pnames": [
                "a",
                "b"
            ]
        },
        "vmin": 0.0,
        "vmax": 0.0,
        "xmin": 2.85,
        "xmax": 3.0
    },
    "__xmin": [
        0.0,
        0.15,
        0.3,
        0.45,
        0.6,
        0.75,
        0.9,
        1.05,
        1.2,
        1.35,
        1.5,
        1.65,
        1.8,
        1.95,
        2.1,
        2.25,
        2.4,
        2.55,
        2.7,
        2.85,
        0.0,
        0.15,
        0.3,
        0.45,
        0.6,
        0.75,
        0.9,
        1.05,
        1.2,
        1.35,
        1.5,
        1.65,
        1.8,
        1.95,
        2.1,
        2.25,
        2.4,
        2.55,
        2.7,
        2.85
    ],
    "__xmax": [
        0.15,
        0.3,
        0.45,
        0.6,
        0.75,
        0.9,
        1.05,
        1.2,
        1.35,
        1.5,
        1.65,
        1.8,
        1.95,
        2.1,
        2.25,
        2.4,
        2.55,
        2.7,
        2.85,
        3.0,
        0.15,
        0.3,
        0.45,
        0.6,
        0.75,
        0.9,
        1.05,
        1.2,
        1.35,
        1.5,
        1.65,
        1.8,
        1.95,
        2.1,
        2.25,
        2.4,
        2.55,
        2.7,
        2.85,
        3.0
    ]
}